{
  "project": "hivemind",
  "description": "Changelog for Hivemind - Local-first observable orchestration for agentic development",
  "format_version": "1.0.0",
  "entries": [
    {
      "version": "v0.1.3",
      "date": "2026-02-07",
      "phase": 13,
      "changes": [
        {
          "type": "added",
          "area": "adapters",
          "description": "Align runtime adapter contract with Initialize/Prepare/Execute/Terminate lifecycle"
        },
        {
          "type": "added",
          "area": "core",
          "description": "Add persisted runtime lifecycle events (RuntimeStarted/RuntimeOutputChunk/RuntimeExited/RuntimeTerminated)"
        },
        {
          "type": "changed",
          "area": "cli",
          "description": "Extend event listing to label runtime lifecycle events"
        }
      ]
    },
    {
      "version": "v0.1.2",
      "date": "2026-02-07",
      "phase": 11,
      "changes": [
        {
          "type": "added",
          "area": "core",
          "description": "Create isolated git worktrees per task under .hivemind/worktrees"
        },
        {
          "type": "added",
          "area": "cli",
          "description": "Add worktree CLI commands: worktree list, inspect, cleanup"
        },
        {
          "type": "changed",
          "area": "core",
          "description": "Provision task worktrees on flow start and clean up on verification success (configurable)"
        }
      ]
    },
    {
      "version": "v0.1.1",
      "date": "2026-02-06",
      "phase": 0,
      "changes": [
        {
          "type": "changed",
          "area": "ci",
          "description": "Run the test suite with cargo-nextest in CI"
        },
        {
          "type": "changed",
          "area": "ci",
          "description": "Prefer cargo-nextest locally when available (Makefile)"
        }
      ]
    }
  ]
}
